[
 {
  "module": "text_representation",
  "kind": "mim",
  "svg": "mimexpg1.svg",
  "num": "1",
  "ocr": "presentation_definition _schema",
  "ref": "presentation_definition_schema",
  "score": 100,
  "method": "schema->primary",
  "flag": "convention"
 },
 {
  "module": "text_representation",
  "kind": "mim",
  "svg": "mimexpg1.svg",
  "num": "2",
  "ocr": "presentation_resource_schema",
  "ref": "presentation_resource_schema",
  "score": 100,
  "method": "schema->primary",
  "flag": "convention"
 },
 {
  "module": "text_representation",
  "kind": "mim",
  "svg": "mimexpg1.svg",
  "num": "3",
  "ocr": "Associative text mim",
  "ref": "Associative_text_mim.short_listing",
  "score": 100,
  "method": "schema->primary",
  "flag": "convention"
 },
 {
  "module": "text_representation",
  "kind": "mim",
  "svg": "mimexpg1.svg",
  "num": "4",
  "ocr": "Text appearance_mim",
  "ref": "Text_appearance_mim.short_listing",
  "score": 100,
  "method": "schema->primary",
  "flag": "convention"
 }
]